uk_bin_collection/Local_Authority_Boundaries.geojson
uk_bin_collection/README.rst
uk_bin_collection/compare_lad_codes.py
uk_bin_collection/map.html
uk_bin_collection/tests/check_selenium_url_in_input.json.py
uk_bin_collection/tests/council_feature_input_parity.py
uk_bin_collection/tests/features/environment.py
uk_bin_collection/tests/features/validate_council_outputs.feature
uk_bin_collection/tests/generate_map_test_results.py
uk_bin_collection/tests/input.json
uk_bin_collection/tests/output.schema
uk_bin_collection/tests/step_defs/step_helpers/file_handler.py
uk_bin_collection/tests/step_defs/test_validate_council.py
uk_bin_collection/tests/test_collect_data.py
uk_bin_collection/tests/test_common_functions.py
uk_bin_collection/tests/test_conftest.py
uk_bin_collection/tests/test_get_data.py
uk_bin_collection/uk_bin_collection/collect_data.py
uk_bin_collection/uk_bin_collection/common.py
uk_bin_collection/uk_bin_collection/councils/AberdeenCityCouncil.py
uk_bin_collection/uk_bin_collection/councils/AberdeenshireCouncil.py
uk_bin_collection/uk_bin_collection/councils/AdurAndWorthingCouncils.py
uk_bin_collection/uk_bin_collection/councils/AmberValleyBoroughCouncil.py
uk_bin_collection/uk_bin_collection/councils/AngusCouncil.py
uk_bin_collection/uk_bin_collection/councils/AntrimAndNewtonabbeyCouncil.py
uk_bin_collection/uk_bin_collection/councils/ArdsAndNorthDownCouncil.py
uk_bin_collection/uk_bin_collection/councils/ArgyllandButeCouncil.py
uk_bin_collection/uk_bin_collection/councils/ArmaghBanbridgeCraigavonCouncil.py
uk_bin_collection/uk_bin_collection/councils/ArunCouncil.py
uk_bin_collection/uk_bin_collection/councils/AshfieldDistrictCouncil.py
uk_bin_collection/uk_bin_collection/councils/AshfordBoroughCouncil.py
uk_bin_collection/uk_bin_collection/councils/BCPCouncil.py
uk_bin_collection/uk_bin_collection/councils/BaberghDistrictCouncil.py
uk_bin_collection/uk_bin_collection/councils/BarkingDagenham.py
uk_bin_collection/uk_bin_collection/councils/BarnetCouncil.py
uk_bin_collection-0.162.5.dist-info/LICENSE
uk_bin_collection-0.162.5.dist-info/METADATA
uk_bin_collection-0.162.5.dist-info/WHEEL
uk_bin_collection-0.162.5.dist-info/entry_points.txt
uk_bin_collection-0.162.5.dist-info/RECORD
