Metadata-Version: 2.1
Name: uk_bin_collection
Version: 0.162.5
Summary: Python Lib to collect UK Bin Data
Author: Robert Bradley
Author-email: robbrad182@gmail.com
Requires-Python: >=3.12,<3.14
Classifier: Programming Language :: Python :: 3
Classifier: Programming Language :: Python :: 3.12
Classifier: Programming Language :: Python :: 3.13
Provides-Extra: ocr
Requires-Dist: bs4
Requires-Dist: easyocr (>=1.7.0,<2.0.0) ; extra == "ocr"
Requires-Dist: holidays
Requires-Dist: icalevents (>=0.2.1,<0.3.0)
Requires-Dist: lxml
Requires-Dist: pandas
Requires-Dist: pillow (>=10.0.0) ; extra == "ocr"
Requires-Dist: python-dateutil
Requires-Dist: requests
Requires-Dist: selenium
Requires-Dist: tabulate (>=0.9.0,<0.10.0)
Requires-Dist: urllib3
Requires-Dist: webdriver-manager (>=4.0.1,<5.0.0)
Project-URL: issues, https://github.com/robbrad/UKBinCollectionData/issues
